submitty_config/__init__.py
submitty_config/__main__.py
submitty_config/main.py
submitty_config/schema.json
submitty_config-0.4.0.dist-info/METADATA
submitty_config-0.4.0.dist-info/RECORD
submitty_config-0.4.0.dist-info/WHEEL
submitty_config-0.4.0.dist-info/entry_points.txt
submitty_config-0.4.0.dist-info/top_level.txt
