Metadata-Version: 2.1
Name: submitty-config
Version: 0.4.0
Summary: My short description for my project.
Home-page: https://github.com/Submitty/submitty-config
Author: Matthew Peveler
Author-email: matt.peveler@gmail.com
License: MIT
Platform: UNKNOWN
Classifier: Development Status :: 3 - Alpha
Classifier: Environment :: Console
Classifier: Intended Audience :: Education
Classifier: License :: OSI Approved :: MIT License
Classifier: Programming Language :: Python
Classifier: Programming Language :: Python :: 3
Classifier: Programming Language :: Python :: 3.4
Classifier: Programming Language :: Python :: 3.5
Classifier: Programming Language :: Python :: 3.6
Classifier: Topic :: Utilities
Requires-Python: >=3.4.0
Requires-Dist: jsonschema
